choicesfields/__init__.py
django_choicesfields-0.1.1.dist-info/WHEEL
django_choicesfields-0.1.1.dist-info/METADATA
django_choicesfields-0.1.1.dist-info/RECORD
