Metadata-Version: 2.1
Name: django-choicesfields
Version: 0.1.1
Summary: Django fields for modern choices
License: MIT
Author: Alexander Viklund
Author-email: bullfest@sthlm.dev
Requires-Python: >=3.6
Classifier: License :: OSI Approved :: MIT License
Classifier: Programming Language :: Python :: 3
Classifier: Programming Language :: Python :: 3.6
Classifier: Programming Language :: Python :: 3.7
Classifier: Programming Language :: Python :: 3.8
Requires-Dist: django (>=3.0.0)
